metzctl/__init__.py
metzctl/__main__.py
metzctl/remote.py
metzctl-1.0.0.dist-info/LICENSE
metzctl-1.0.0.dist-info/METADATA
metzctl-1.0.0.dist-info/WHEEL
metzctl-1.0.0.dist-info/entry_points.txt
metzctl-1.0.0.dist-info/top_level.txt
metzctl-1.0.0.dist-info/RECORD
