Metadata-Version: 2.1
Name: metzctl
Version: 1.0.0
Summary: Remote control for Metz televisions
Home-page: https://github.com/kaoh/metzctl
Author: Karsten Ohme
Author-email: k_o_@users.sourceforge.net
License: LGPLv3
Platform: UNKNOWN
Classifier: License :: OSI Approved :: GNU General Public License v3 (GPLv3)
Classifier: Programming Language :: Python :: 3
Classifier: Programming Language :: Python :: 3.6
Requires-Dist: getmac
Requires-Dist: wakeonlan
